rox_vectors/__init__.py
rox_vectors/py.typed
rox_vectors/vectors.py
rox_vectors/version.py
rox_vectors-0.2.3.dist-info/licenses/LICENCE
rox_vectors-0.2.3.dist-info/METADATA
rox_vectors-0.2.3.dist-info/WHEEL
rox_vectors-0.2.3.dist-info/top_level.txt
rox_vectors-0.2.3.dist-info/RECORD
