Metadata-Version: 2.4
Name: rox-vectors
Version: 0.2.3
Summary: 2D vector classes
Author-email: ROX Automation <jev@roxautomation.com>
License-Expression: MIT
Project-URL: Homepage, https://gitlab.com/roxautomation/components/rox-vectors
Classifier: Development Status :: 3 - Alpha
Classifier: Intended Audience :: Developers
Classifier: Operating System :: OS Independent
Classifier: Programming Language :: Python
Classifier: Programming Language :: Python :: 3.10
Classifier: Topic :: Software Development :: Libraries :: Python Modules
Classifier: Typing :: Typed
Requires-Python: >=3.10
License-File: LICENCE
Provides-Extra: dev
Requires-Dist: bumpversion; extra == "dev"
Requires-Dist: click; extra == "dev"
Requires-Dist: invoke; extra == "dev"
Requires-Dist: ipython; extra == "dev"
Requires-Dist: mypy; extra == "dev"
Requires-Dist: numpy; extra == "dev"
Requires-Dist: pre-commit; extra == "dev"
Requires-Dist: pytest; extra == "dev"
Requires-Dist: pytest-asyncio; extra == "dev"
Requires-Dist: pytest-cov; extra == "dev"
Requires-Dist: ruff; extra == "dev"
Dynamic: license-file
